{
  "productos": [
    {
      "nombre": "Pulpitos",
      "imagen": "ami/assets/img/Pulpitos.jpeg",
      "precio": "₡XXX",
      "descripcion": "Suaves y adorables, perfectos para acompañarte en cualquier momento."
    },
    {
      "nombre": "Sirenita",
      "imagen": "ami/assets/img/Poratadita Sirena.jpeg",
      "precio": "₡XXX",
      "descripcion": "Inspirada en el mar, ideal para quienes aman lo mágico y delicado.."
    },
    
    {
      "nombre": "Tortuguita",
      "imagen": "ami/assets/img/Tortuguita.jpeg",
      "precio": "₡XXX",
      "descripcion": "Divertido y único, con un toque juguetón que encanta."
    },

    {
      "nombre": "Cocodrilito",
      "imagen": "ami/assets/img/Cocodrilito.jpeg",
      "precio": "₡XXX",
      "descripcion": "Detalle tierno y colorido."
    },

    {
      "nombre": "Nachito Payacito",
      "imagen": "ami/assets/img/Ami Pelinaranja.jpeg",
      "precio": "₡XXX",
      "descripcion": "Colorido y alegre, perfecto para sacar sonrisas.."
    },

    {
      "nombre": "Bailarina",
      "imagen": "ami/assets/img/Bailarina.jpeg",
      "precio": "₡XXX",
      "descripcion": "Elegante y delicada, hecha con detalles llenos de amor."
    },

    {
      "nombre": "Conejita",
      "imagen": "ami/assets/img/Conejita.jpeg",
      "precio": "₡XXX",
      "descripcion": "Suavecita y encantadora, ideal para decorar o regalar."
    },

    {
      "nombre": "Dinito Stacking Rings",
      "imagen": "ami/assets/img/Dinito Vista 1.jpeg",
      "precio": "₡XXX",
      "descripcion": "Interactivo y creativo, perfecto para jugar y armar.."
    },

    {
      "nombre": "Dino el Dinosaurio",
      "imagen": "ami/assets/img/Dino Colorido V1.jpeg",
      "precio": "₡XXX",
      "descripcion": "Detalle tierno y colorido."
    },


    {
      "nombre": "Dinito con Gorrito",
      "imagen": "ami/assets/img/Dino Gorrito V1.jpeg",
      "precio": "₡XXX",
      "descripcion": "Detalle tierno y colorido."
    },

    {
      "nombre": "Dragoncito",
      "imagen": "ami/assets/img/Dragoncito.jpeg",
      "precio": "₡XXX",
      "descripcion": "Mágico y único, ideal para amantes de la fantasía."
    },

    {
      "nombre": "AMI's",
      "imagen": "ami/assets/img/Grupito de AMIs V1.jpeg",
      "precio": "₡XXX",
      "descripcion": "Colección de personajes únicos hechos con dedicación."
    },

    {
      "nombre": "Dinomóvil",
      "imagen": "ami/assets/img/Grupito Dinos.jpeg",
      "precio": "₡XXX",
      "descripcion": "Creativo y divertido, combina imaginación y ternura."
    },

    {
      "nombre": "Hamstercito",
      "imagen": "ami/assets/img/Hamstercito.jpeg",
      "precio": "₡XXX",
      "descripcion": "Pequeñito y tierno, imposible no enamorarse."
    },

    {
      "nombre": "Jirafita y Leoncito",
      "imagen": "ami/assets/img/Jirafita y Leo.jpeg",
      "precio": "₡XXX",
      "descripcion": "Dúo adorable que transmite ternura y amistad."
    },

    {
      "nombre": "Mariposita Beige",
      "imagen": "ami/assets/img/Mariposita Beige.jpeg",
      "precio": "₡XXX",
      "descripcion": "Suave y delicada, inspirada en la belleza natural y los tonos cálidos."
    },

    {
      "nombre": "Mariposita Negra",
      "imagen": "ami/assets/img/Mariposita Negra.jpeg",
      "precio": "₡XXX",
      "descripcion": "Elegante y única, con un estilo moderno y lleno de carácter."
    },

    {
      "nombre": "Mounstruito",
      "imagen": "ami/assets/img/Mounstruito.jpeg",
      "precio": "₡XXX",
      "descripcion": "Divertido y travieso, perfecto para quienes aman lo diferente."
    },
    
    {
      "nombre": "Muñequita Pelinegra",
      "imagen": "ami/assets/img/Muñe Pelinegra V2.jpeg",
      "descripcion": "Versión alternativa con detalles encantadores."
    },
    
    {
      "nombre": "Muñequita Peliroja",
      "imagen": "ami/assets/img/Muñe Peliroja V1.jpeg",
      "descripcion": "Color vibrante que transmite alegría y calidez."
    },
    
    {
      "nombre": "Osita",
      "imagen": "ami/assets/img/Osita.jpeg",
      "descripcion": "Suave y adorable, perfecta compañía."
    },
    
    {
      "nombre": "Teddy Bear",
      "imagen": "ami/assets/img/Osito.jpeg",
      "descripcion": "Clásico y tierno, nunca pasa de moda."
    },
    
    {
      "nombre": "Perrito",
      "imagen": "ami/assets/img/Perrito.jpeg",
      "descripcion": "Fiel, tierno y listo para acompañarte."
    },
    
    {
      "nombre": "Ramito de flores",
      "imagen": "ami/assets/img/Ramito Flores.jpeg",
      "descripcion": "Detalle perfecto lleno de amor."
    },
    
    {
      "nombre": "Ramito de tulipanes",
      "imagen": "ami/assets/img/Ramito Tulipanes.jpeg",
      "descripcion": "Elegante y delicado, ideal para regalar."
    },
    
    {
      "nombre": "Ratoncita",
      "imagen": "ami/assets/img/Ratoncita.jpeg",
      "descripcion": "Pequeña y dulce, llena de encanto."
    },
    
    {
      "nombre": "Tortuguita",
      "imagen": "ami/assets/img/Tortuguita.jpeg",
      "descripcion": "Símbolo de calma y ternura."
    },
    
    {
      "nombre": "Unicornio celeste",
      "imagen": "ami/assets/img/Unicornio Pelito Celeste.jpeg",
      "descripcion": "Mágico y suave, lleno de fantasía."
    },
    {
      "nombre": "Unicornio rosado",
      "imagen": "ami/assets/img/Unicornio Pelito Rosa.jpeg",
      "descripcion": "Dulce y encantador, perfecto para soñar."
    },
    
    {
      "nombre": "Virgencita",
      "imagen": "ami/assets/img/Virgencita.jpeg",
      "descripcion": "Especial y significativa, hecha con dedicación."
    },

    {
      "nombre": "Salchichita",
      "imagen": "ami/assets/img/Salchichita.jpg",
      "descripcion": "Simple, especial y auténtica."
    },

    {
      "nombre": "Llaverito",
      "imagen": "ami/assets/img/Llavero.jpeg",
      "descripcion": "Ideal para decorar."
    },

    {
      "nombre": "Conejita Elegante",
      "imagen": "ami/assets/img/Conejita Ropa.jpg",
      "descripcion": "Coqueta y leal."
    },

    {
      "nombre": "Anne con E",
      "imagen": "ami/assets/img/Anne con E.jpg",
      "descripcion": "Un detalle que guarda historias en silencio."
    },

    {
      "nombre": "Conejita con Sombrero",
      "imagen": "ami/assets/img/Conejita Sombrero.jpg",
      "descripcion": "Derrocha ternura y elegancia."
    },

    {
      "nombre": "Adornito de Unicornios",
      "imagen": "ami/assets/img/Adornito.jpg",
      "descripcion": "Lo que se necesita para darle personalidad a tu dormitorio."
    },

    {
      "nombre": "Meli, Lupe y Lily",
      "imagen": "ami/assets/img/Conejitas.png",
      "descripcion": "Amigas inseparables."
    },

    {
      "nombre": "Ratoncita",
      "imagen": "ami/assets/img/Ratoncita.jpeg",
      "descripcion": "Pequeña ratoncita crochet, suave y encantadora,"
    }
  ]
}
